marabunta/__init__.py
marabunta/__main__.py
marabunta/config.py
marabunta/core.py
marabunta/database.py
marabunta/exception.py
marabunta/helpers.py
marabunta/model.py
marabunta/output.py
marabunta/parser.py
marabunta/runner.py
marabunta/version.py
marabunta/web.py
marabunta/html/migration.html
marabunta-0.14.0.dist-info/licenses/AUTHORS.rst
marabunta-0.14.0.dist-info/licenses/LICENSE
marabunta-0.14.0.dist-info/METADATA
marabunta-0.14.0.dist-info/WHEEL
marabunta-0.14.0.dist-info/entry_points.txt
marabunta-0.14.0.dist-info/top_level.txt
marabunta-0.14.0.dist-info/RECORD
